chittorgarh_client/__init__.py
chittorgarh_client/client.py
chittorgarh_client/mapper.py
chittorgarh_client/models.py
chittorgarh_client/utils.py
tests/__init__.py
chittorgarh_client-1.0.37.dist-info/METADATA
chittorgarh_client-1.0.37.dist-info/WHEEL
chittorgarh_client-1.0.37.dist-info/top_level.txt
chittorgarh_client-1.0.37.dist-info/RECORD
