Metadata-Version: 2.4
Name: chittorgarh_client
Version: 1.0.37
Summary: Unofficial chittorgarh.com client
Home-page: https://github.com/dhaval-mehta/chittorgarh-client
Author: Dhaval Mehta
Keywords: chittorgarh
Requires-Python: >=3.7, <4
Requires-Dist: requests
Requires-Dist: lxml
Dynamic: author
Dynamic: description
Dynamic: home-page
Dynamic: keywords
Dynamic: requires-dist
Dynamic: requires-python
Dynamic: summary
